{
  "mode": "hhcw",
  "chart": {
    "695908": 25,
    "695909": 11,
    "695910": 10,
    "695911": 14,
    "695912": 22,
    "695913": 12,
    "695914": 6,
    "695915": 3,
    "695916": 7,
    "695917": 7,
    "695918": 13,
    "null": null
  },
  "images": [
    "https://sirekap-obj-formc.kpu.go.id/ab42/pemilu/pdpd/33/26/09/20/23/3326092023007-20240218-155746--845185ca-0b26-4d4a-acf4-ecc5dca83738.jpg",
    "https://sirekap-obj-formc.kpu.go.id/ab42/pemilu/pdpd/33/26/09/20/23/3326092023007-20240218-160009--96f04921-6e6f-4398-9458-36160eae866a.jpg",
    "https://sirekap-obj-formc.kpu.go.id/ab42/pemilu/pdpd/33/26/09/20/23/3326092023007-20240218-160116--4232df91-39d8-4c6e-a097-21ecfaf419c4.jpg"
  ],
  "administrasi": {
    "suara_sah": 130,
    "suara_total": 213,
    "pemilih_dpt_j": 272,
    "pemilih_dpt_l": 151,
    "pemilih_dpt_p": 121,
    "pengguna_dpt_j": 212,
    "pengguna_dpt_l": 106,
    "pengguna_dpt_p": 106,
    "pengguna_dptb_j": 0,
    "pengguna_dptb_l": 0,
    "pengguna_dptb_p": 0,
    "suara_tidak_sah": 83,
    "pengguna_total_j": 213,
    "pengguna_total_l": 106,
    "pengguna_total_p": 107,
    "pengguna_non_dpt_j": 1,
    "pengguna_non_dpt_l": 0,
    "pengguna_non_dpt_p": 1
  },
  "psu": null,
  "ts": "2024-02-19 06:15:00",
  "status_suara": true,
  "status_adm": true
}