{
  "mode": "hhcw",
  "chart": {
    "695928": 27,
    "695929": 28,
    "695930": 18,
    "695931": 12,
    "695932": 23,
    "695933": 6,
    "695934": 2,
    "695935": 2,
    "695936": 0,
    "695937": 18,
    "695938": 3,
    "695939": 33,
    "695940": 3,
    "null": null
  },
  "images": [
    "https://sirekap-obj-formc.kpu.go.id/9429/pemilu/pdpd/35/17/17/20/06/3517172006004-20240214-224344--d1737137-4563-40f5-8390-271acd681d0f.jpg",
    "https://sirekap-obj-formc.kpu.go.id/9429/pemilu/pdpd/35/17/17/20/06/3517172006004-20240217-173400--bb01d5ac-22e6-4f2a-8892-5b1033e0ae41.jpg",
    "https://sirekap-obj-formc.kpu.go.id/9429/pemilu/pdpd/35/17/17/20/06/3517172006004-20240217-173400--fa01a312-62d2-4b42-98f2-9d90f3643ecf.jpg",
    "https://sirekap-obj-formc.kpu.go.id/9429/pemilu/pdpd/35/17/17/20/06/3517172006004-20240217-173359--d8a62996-ec5e-4a3b-bb94-72a4fe38cef5.jpg"
  ],
  "administrasi": {
    "suara_sah": 175,
    "suara_total": 231,
    "pemilih_dpt_j": 274,
    "pemilih_dpt_l": 138,
    "pemilih_dpt_p": 136,
    "pengguna_dpt_j": 231,
    "pengguna_dpt_l": 115,
    "pengguna_dpt_p": 116,
    "pengguna_dptb_j": 0,
    "pengguna_dptb_l": 0,
    "pengguna_dptb_p": 0,
    "suara_tidak_sah": 56,
    "pengguna_total_j": 231,
    "pengguna_total_l": 115,
    "pengguna_total_p": 116,
    "pengguna_non_dpt_j": 0,
    "pengguna_non_dpt_l": 0,
    "pengguna_non_dpt_p": 0
  },
  "psu": null,
  "ts": "2024-02-17 18:00:00",
  "status_suara": true,
  "status_adm": true
}