{
  "mode": "hhcw",
  "chart": {
    "695854": 4,
    "695855": 11,
    "695856": 0,
    "695857": 11,
    "695858": 1,
    "695859": 7,
    "695860": 6,
    "695861": 1,
    "695862": 1,
    "695863": 50,
    "695864": 5,
    "695865": 0,
    "695866": 0,
    "695867": 4,
    "695868": 6,
    "695869": 0,
    "695870": 4,
    "695871": 1,
    "695872": 1,
    "695873": 1,
    "695874": 0,
    "695875": 8,
    "695876": 0,
    "695877": 2,
    "695878": 0,
    "695879": 0,
    "695880": 0,
    "695881": 1,
    "695882": 1,
    "695883": 0,
    "695884": 0,
    "695885": 0,
    "695886": 0,
    "695887": 50,
    "695888": 0,
    "695889": 0,
    "695890": 2,
    "695891": 2,
    "695892": 10,
    "695893": 0,
    "695894": 5,
    "695895": 0,
    "695896": 0,
    "695897": 0,
    "695898": 1,
    "695899": 0,
    "695900": 0,
    "695901": 0,
    "695902": 0,
    "695903": 2,
    "695904": 0,
    "695905": 0,
    "695906": 1,
    "695907": 0,
    "null": null
  },
  "images": [
    "https://sirekap-obj-formc.kpu.go.id/c69e/pemilu/pdpd/32/14/06/20/01/3214062001014-20240217-120948--51989f2a-0939-486e-a935-0855d1898ad4.jpg",
    "https://sirekap-obj-formc.kpu.go.id/c69e/pemilu/pdpd/32/14/06/20/01/3214062001014-20240217-121434--5e631c01-88a4-4c83-a292-6e97b0c17ef3.jpg",
    "https://sirekap-obj-formc.kpu.go.id/c69e/pemilu/pdpd/32/14/06/20/01/3214062001014-20240217-121545--214c641b-ca29-409d-b0e7-dbfccefccdca.jpg",
    "https://sirekap-obj-formc.kpu.go.id/c69e/pemilu/pdpd/32/14/06/20/01/3214062001014-20240217-121641--b90f07d4-6ada-4c46-8d36-d49cd721c857.jpg",
    "https://sirekap-obj-formc.kpu.go.id/c69e/pemilu/pdpd/32/14/06/20/01/3214062001014-20240217-121730--211539c5-9471-4c71-8de9-8a20c4111784.jpg",
    "https://sirekap-obj-formc.kpu.go.id/c69e/pemilu/pdpd/32/14/06/20/01/3214062001014-20240217-121818--2fa6ab72-4667-4b3c-9629-e94cd99d953a.jpg",
    "https://sirekap-obj-formc.kpu.go.id/c69e/pemilu/pdpd/32/14/06/20/01/3214062001014-20240217-121857--b9f53e1a-e924-4234-83e5-6ac1dbdb4efb.jpg"
  ],
  "administrasi": {
    "suara_sah": 199,
    "suara_total": 247,
    "pemilih_dpt_j": 275,
    "pemilih_dpt_l": 134,
    "pemilih_dpt_p": 141,
    "pengguna_dpt_j": 239,
    "pengguna_dpt_l": 114,
    "pengguna_dpt_p": 125,
    "pengguna_dptb_j": 8,
    "pengguna_dptb_l": 4,
    "pengguna_dptb_p": 4,
    "suara_tidak_sah": 48,
    "pengguna_total_j": 247,
    "pengguna_total_l": 118,
    "pengguna_total_p": 129,
    "pengguna_non_dpt_j": 0,
    "pengguna_non_dpt_l": 0,
    "pengguna_non_dpt_p": 0
  },
  "psu": null,
  "ts": "2024-02-17 14:45:17",
  "status_suara": true,
  "status_adm": true
}