{
  "chart": {
    "695908": 26,
    "695909": 7,
    "695910": 4,
    "695911": 16,
    "695912": 36,
    "695913": 17,
    "695914": 2,
    "695915": 7,
    "695916": 14,
    "695917": 11,
    "695918": 33,
    "null": null
  },
  "images": [
    "https://sirekap-obj-formc.kpu.go.id/2e0e/pemilu/pdpd/33/08/09/10/04/3308091004009-20240216-080509--c60a54fc-9731-408d-81cb-b9afc3159c6e.jpg",
    "https://sirekap-obj-formc.kpu.go.id/2e0e/pemilu/pdpd/33/08/09/10/04/3308091004009-20240216-080511--10e88f20-30a0-4952-bb46-a1490ceb50ee.jpg",
    "https://sirekap-obj-formc.kpu.go.id/2e0e/pemilu/pdpd/33/08/09/10/04/3308091004009-20240216-080510--5be9dc9d-42aa-4ba3-83ba-8cc4ea2902c7.jpg"
  ],
  "administrasi": {
    "suara_sah": 173,
    "suara_total": 240,
    "pemilih_dpt_j": 274,
    "pemilih_dpt_l": 133,
    "pemilih_dpt_p": 141,
    "pengguna_dpt_j": 234,
    "pengguna_dpt_l": 109,
    "pengguna_dpt_p": 125,
    "pengguna_dptb_j": 6,
    "pengguna_dptb_l": 4,
    "pengguna_dptb_p": 2,
    "suara_tidak_sah": 67,
    "pengguna_total_j": 240,
    "pengguna_total_l": 113,
    "pengguna_total_p": 127,
    "pengguna_non_dpt_j": 0,
    "pengguna_non_dpt_l": 0,
    "pengguna_non_dpt_p": 0
  },
  "psu": null,
  "ts": "2024-02-16 08:31:17",
  "status_suara": true,
  "status_adm": true
}