{
  "chart": {
    "695908": 24,
    "695909": 5,
    "695910": 3,
    "695911": 9,
    "695912": 28,
    "695913": 18,
    "695914": 5,
    "695915": 1,
    "695916": 22,
    "695917": 15,
    "695918": 12,
    "null": null
  },
  "images": [
    "https://sirekap-obj-formc.kpu.go.id/0074/pemilu/pdpd/33/27/13/20/15/3327132015006-20240214-190252--a88e2917-96f0-471e-9ae7-734db241fcbe.jpg",
    "https://sirekap-obj-formc.kpu.go.id/0074/pemilu/pdpd/33/27/13/20/15/3327132015006-20240216-114118--874dd0a1-6598-4764-8887-c620753347e3.jpg",
    "https://sirekap-obj-formc.kpu.go.id/0074/pemilu/pdpd/33/27/13/20/15/3327132015006-20240215-104717--de1e1900-50a3-4ec5-a03c-eb239d57a77e.jpg"
  ],
  "administrasi": {
    "suara_sah": 142,
    "suara_total": 202,
    "pemilih_dpt_j": 263,
    "pemilih_dpt_l": 131,
    "pemilih_dpt_p": 132,
    "pengguna_dpt_j": 201,
    "pengguna_dpt_l": 93,
    "pengguna_dpt_p": 108,
    "pengguna_dptb_j": 0,
    "pengguna_dptb_l": 0,
    "pengguna_dptb_p": 0,
    "suara_tidak_sah": 60,
    "pengguna_total_j": 202,
    "pengguna_total_l": 93,
    "pengguna_total_p": 109,
    "pengguna_non_dpt_j": 1,
    "pengguna_non_dpt_l": 0,
    "pengguna_non_dpt_p": 1
  },
  "psu": null,
  "ts": "2024-02-16 12:52:03",
  "status_suara": true,
  "status_adm": true
}