{
  "chart": {
    "695941": 7,
    "695942": 2,
    "695943": 7,
    "695944": 3,
    "695945": 2,
    "695946": 39,
    "695947": 4,
    "695948": 0,
    "695949": 3,
    "695950": 0,
    "695951": 1,
    "695952": 2,
    "695953": 0,
    "695954": 1,
    "695955": 0,
    "695956": 0,
    "695957": 1,
    "695958": 0,
    "695959": 0,
    "695960": 1,
    "695961": 32,
    "695962": 5,
    "695963": 3,
    "695964": 0
  },
  "images": [
    "https://sirekap-obj-formc.kpu.go.id/7106/pemilu/pdpd/36/04/31/20/12/3604312012007-20240216-134518--16e6bfa9-d4f6-403b-a877-f8155a05cb09.jpg",
    "https://sirekap-obj-formc.kpu.go.id/7106/pemilu/pdpd/36/04/31/20/12/3604312012007-20240216-134519--6f0cd282-96f6-4a48-b36e-32606f1a7d46.jpg",
    "https://sirekap-obj-formc.kpu.go.id/7106/pemilu/pdpd/36/04/31/20/12/3604312012007-20240216-134520--706783a1-295d-4c49-b505-652a2e322dfc.jpg",
    "https://sirekap-obj-formc.kpu.go.id/7106/pemilu/pdpd/36/04/31/20/12/3604312012007-20240216-134519--7271bfc5-b71c-4db4-9a4c-e3fe9482d6b1.jpg"
  ],
  "administrasi": {
    "suara_sah": 113,
    "suara_total": 210,
    "pemilih_dpt_j": 260,
    "pemilih_dpt_l": 134,
    "pemilih_dpt_p": 126,
    "pengguna_dpt_j": 210,
    "pengguna_dpt_l": 113,
    "pengguna_dpt_p": 97,
    "pengguna_dptb_j": 0,
    "pengguna_dptb_l": 0,
    "pengguna_dptb_p": 0,
    "suara_tidak_sah": 97,
    "pengguna_total_j": 210,
    "pengguna_total_l": 113,
    "pengguna_total_p": 97,
    "pengguna_non_dpt_j": 0,
    "pengguna_non_dpt_l": 0,
    "pengguna_non_dpt_p": 0
  },
  "psu": null,
  "ts": "2024-02-16 14:01:43",
  "status_suara": true,
  "status_adm": true
}