{
  "mode": "hhcw",
  "chart": {
    "695928": 12,
    "695929": 17,
    "695930": 6,
    "695931": 15,
    "695932": 9,
    "695933": 38,
    "695934": 3,
    "695935": 1,
    "695936": 0,
    "695937": 17,
    "695938": 2,
    "695939": 24,
    "695940": 0,
    "null": null
  },
  "images": [
    "https://sirekap-obj-formc.kpu.go.id/1288/pemilu/pdpd/35/08/05/20/04/3508052004007-20240218-171824--b0b3fe35-67f3-410c-8529-c8205804d2de.jpg",
    "https://sirekap-obj-formc.kpu.go.id/1288/pemilu/pdpd/35/08/05/20/04/3508052004007-20240218-172150--0f827286-efb9-4fe6-ba14-f149a7a54b18.jpg",
    "https://sirekap-obj-formc.kpu.go.id/1288/pemilu/pdpd/35/08/05/20/04/3508052004007-20240218-172427--81bb567c-0667-4c66-9113-14a12807370f.jpg",
    "https://sirekap-obj-formc.kpu.go.id/1288/pemilu/pdpd/35/08/05/20/04/3508052004007-20240218-172728--2fba995d-2886-41bb-8450-fd94ab065b13.jpg"
  ],
  "administrasi": {
    "suara_sah": 144,
    "suara_total": 192,
    "pemilih_dpt_j": 230,
    "pemilih_dpt_l": 115,
    "pemilih_dpt_p": 115,
    "pengguna_dpt_j": 190,
    "pengguna_dpt_l": 92,
    "pengguna_dpt_p": 98,
    "pengguna_dptb_j": 0,
    "pengguna_dptb_l": 0,
    "pengguna_dptb_p": 0,
    "suara_tidak_sah": 48,
    "pengguna_total_j": 192,
    "pengguna_total_l": 92,
    "pengguna_total_p": 100,
    "pengguna_non_dpt_j": 2,
    "pengguna_non_dpt_l": 0,
    "pengguna_non_dpt_p": 2
  },
  "psu": null,
  "ts": "2024-02-19 06:15:00",
  "status_suara": true,
  "status_adm": true
}