{
  "mode": "hhcw",
  "chart": {
    "695908": 14,
    "695909": 8,
    "695910": 3,
    "695911": 16,
    "695912": 20,
    "695913": 14,
    "695914": 3,
    "695915": 0,
    "695916": 3,
    "695917": 16,
    "695918": 87,
    "null": null
  },
  "images": [
    "https://sirekap-obj-formc.kpu.go.id/ebd4/pemilu/pdpd/33/20/06/10/05/3320061005002-20240216-203808--297050d7-862c-4640-af30-9262937d81ee.jpg",
    "https://sirekap-obj-formc.kpu.go.id/ebd4/pemilu/pdpd/33/20/06/10/05/3320061005002-20240216-203811--7082198a-b095-4fb9-b60c-6ff47ea1e04f.jpg",
    "https://sirekap-obj-formc.kpu.go.id/ebd4/pemilu/pdpd/33/20/06/10/05/3320061005002-20240216-203809--049dfaf2-bad9-40cb-bb38-508a37066d64.jpg"
  ],
  "administrasi": {
    "suara_sah": 184,
    "suara_total": 224,
    "pemilih_dpt_j": 260,
    "pemilih_dpt_l": 135,
    "pemilih_dpt_p": 125,
    "pengguna_dpt_j": 222,
    "pengguna_dpt_l": 113,
    "pengguna_dpt_p": 109,
    "pengguna_dptb_j": 2,
    "pengguna_dptb_l": 1,
    "pengguna_dptb_p": 1,
    "suara_tidak_sah": 40,
    "pengguna_total_j": 224,
    "pengguna_total_l": 114,
    "pengguna_total_p": 110,
    "pengguna_non_dpt_j": 0,
    "pengguna_non_dpt_l": 0,
    "pengguna_non_dpt_p": 0
  },
  "psu": null,
  "ts": "2024-02-16 21:30:58",
  "status_suara": true,
  "status_adm": true
}