{
  "mode": "hhcw",
  "chart": {
    "695829": 15,
    "695830": 5,
    "695831": 8,
    "695832": 11,
    "695833": 4,
    "695834": 14,
    "695835": 12,
    "695836": 7,
    "695837": 22,
    "695838": 8,
    "695839": 7,
    "695840": 2,
    "695841": 5,
    "695842": 3,
    "695843": 0,
    "695844": 3,
    "695845": 0,
    "695846": 28,
    "695847": 5,
    "695848": 8,
    "695849": 2,
    "695850": 10,
    "695851": 0,
    "695852": 1,
    "695853": 3,
    "null": null
  },
  "images": [
    "https://sirekap-obj-formc.kpu.go.id/894c/pemilu/pdpd/31/71/08/10/02/3171081002003-20240217-115043--38c1ae4e-a7a1-443f-a416-b7bd5eb4be7e.jpg",
    "https://sirekap-obj-formc.kpu.go.id/894c/pemilu/pdpd/31/71/08/10/02/3171081002003-20240215-005815--bdb74d8e-1bcd-42bb-b05c-e4945c3842af.jpg",
    "https://sirekap-obj-formc.kpu.go.id/894c/pemilu/pdpd/31/71/08/10/02/3171081002003-20240217-115045--d2ec0825-8b21-40ad-ab20-bf116a27e029.jpg",
    "https://sirekap-obj-formc.kpu.go.id/894c/pemilu/pdpd/31/71/08/10/02/3171081002003-20240215-010229--884b0ea6-a0c8-4e76-9ef8-3dc99d8126b5.jpg",
    "https://sirekap-obj-formc.kpu.go.id/894c/pemilu/pdpd/31/71/08/10/02/3171081002003-20240217-115044--9707b46a-d765-4d21-a6bb-4b3f9ecada09.jpg"
  ],
  "administrasi": {
    "suara_sah": 182,
    "suara_total": 215,
    "pemilih_dpt_j": 261,
    "pemilih_dpt_l": 136,
    "pemilih_dpt_p": 125,
    "pengguna_dpt_j": 206,
    "pengguna_dpt_l": 104,
    "pengguna_dpt_p": 102,
    "pengguna_dptb_j": 6,
    "pengguna_dptb_l": 3,
    "pengguna_dptb_p": 3,
    "suara_tidak_sah": 33,
    "pengguna_total_j": 215,
    "pengguna_total_l": 109,
    "pengguna_total_p": 106,
    "pengguna_non_dpt_j": 3,
    "pengguna_non_dpt_l": 2,
    "pengguna_non_dpt_p": 1
  },
  "psu": null,
  "ts": "2024-02-17 12:00:00",
  "status_suara": true,
  "status_adm": true
}