{
  "mode": "hhcw",
  "chart": {
    "695771": 10,
    "695772": 5,
    "695773": 0,
    "695774": 1,
    "695775": 42,
    "695776": 0,
    "695777": 17,
    "695778": 1,
    "695779": 16,
    "695780": 0,
    "695781": 25,
    "695782": 55
  },
  "images": [
    "https://sirekap-obj-formc.kpu.go.id/26d3/pemilu/pdpd/17/01/04/20/26/1701042026003-20240216-232633--719fdb52-2333-4ade-8a01-52748f923084.jpg",
    "https://sirekap-obj-formc.kpu.go.id/26d3/pemilu/pdpd/17/01/04/20/26/1701042026003-20240216-232635--203d9949-1828-4e2b-9bed-dc71a6f47dfe.jpg",
    "https://sirekap-obj-formc.kpu.go.id/26d3/pemilu/pdpd/17/01/04/20/26/1701042026003-20240216-232634--07467bc5-6858-4efd-8466-9f67152ac22a.jpg"
  ],
  "administrasi": {
    "suara_sah": 171,
    "suara_total": 186,
    "pemilih_dpt_j": 193,
    "pemilih_dpt_l": 100,
    "pemilih_dpt_p": 93,
    "pengguna_dpt_j": 178,
    "pengguna_dpt_l": 90,
    "pengguna_dpt_p": 88,
    "pengguna_dptb_j": 5,
    "pengguna_dptb_l": 2,
    "pengguna_dptb_p": 3,
    "suara_tidak_sah": 15,
    "pengguna_total_j": 186,
    "pengguna_total_l": 95,
    "pengguna_total_p": 91,
    "pengguna_non_dpt_j": 3,
    "pengguna_non_dpt_l": 3,
    "pengguna_non_dpt_p": 0
  },
  "psu": null,
  "ts": "2024-02-16 23:30:00",
  "status_suara": true,
  "status_adm": true
}