{
  "chart": {
    "695928": 9,
    "695929": 34,
    "695930": 6,
    "695931": 30,
    "695932": 30,
    "695933": 9,
    "695934": 0,
    "695935": 6,
    "695936": 2,
    "695937": 27,
    "695938": 2,
    "695939": 11,
    "695940": 3,
    "null": null
  },
  "images": [
    "https://sirekap-obj-formc.kpu.go.id/8fd2/pemilu/pdpd/35/10/16/10/03/3510161003024-20240216-054802--faae0766-312d-4e8a-9b20-650bc2bebd74.jpg",
    "https://sirekap-obj-formc.kpu.go.id/8fd2/pemilu/pdpd/35/10/16/10/03/3510161003024-20240214-213500--a2f10c1e-74d7-4ea4-8925-b66a11d116c7.jpg",
    "https://sirekap-obj-formc.kpu.go.id/8fd2/pemilu/pdpd/35/10/16/10/03/3510161003024-20240216-054808--be8d5a60-8733-4f59-8fe5-a5df794a260a.jpg",
    "https://sirekap-obj-formc.kpu.go.id/8fd2/pemilu/pdpd/35/10/16/10/03/3510161003024-20240216-054802--f3016cd2-c834-4f9f-a7f9-f7a5a0927989.jpg"
  ],
  "administrasi": {
    "suara_sah": 169,
    "suara_total": 203,
    "pemilih_dpt_j": 277,
    "pemilih_dpt_l": 125,
    "pemilih_dpt_p": 152,
    "pengguna_dpt_j": 200,
    "pengguna_dpt_l": 87,
    "pengguna_dpt_p": 113,
    "pengguna_dptb_j": 3,
    "pengguna_dptb_l": 1,
    "pengguna_dptb_p": 2,
    "suara_tidak_sah": 34,
    "pengguna_total_j": 203,
    "pengguna_total_l": 88,
    "pengguna_total_p": 115,
    "pengguna_non_dpt_j": 0,
    "pengguna_non_dpt_l": 0,
    "pengguna_non_dpt_p": 0
  },
  "psu": null,
  "ts": "2024-02-16 06:01:13",
  "status_suara": true,
  "status_adm": true
}