{
  "mode": "hhcw",
  "chart": {
    "695928": 19,
    "695929": 48,
    "695930": 14,
    "695931": 12,
    "695932": 11,
    "695933": 13,
    "695934": 1,
    "695935": 2,
    "695936": 0,
    "695937": 16,
    "695938": 0,
    "695939": 19,
    "695940": 1,
    "null": null
  },
  "images": [
    "https://sirekap-obj-formc.kpu.go.id/a512/pemilu/pdpd/35/26/08/20/11/3526082011005-20240216-143406--27fe781e-2266-4936-b7fb-d441a45874ce.jpg",
    "https://sirekap-obj-formc.kpu.go.id/a512/pemilu/pdpd/35/26/08/20/11/3526082011005-20240216-143407--98b23009-382d-4b61-8cd2-11bfa47403a4.jpg",
    "https://sirekap-obj-formc.kpu.go.id/a512/pemilu/pdpd/35/26/08/20/11/3526082011005-20240216-143408--f1f5d0e7-8bd6-42b0-b213-bc3278e1cd7e.jpg",
    "https://sirekap-obj-formc.kpu.go.id/a512/pemilu/pdpd/35/26/08/20/11/3526082011005-20240216-143407--f4d5a128-b21b-41fe-95e5-00314eae6361.jpg"
  ],
  "administrasi": {
    "suara_sah": 156,
    "suara_total": 190,
    "pemilih_dpt_j": 262,
    "pemilih_dpt_l": 115,
    "pemilih_dpt_p": 147,
    "pengguna_dpt_j": 189,
    "pengguna_dpt_l": 87,
    "pengguna_dpt_p": 102,
    "pengguna_dptb_j": 0,
    "pengguna_dptb_l": 0,
    "pengguna_dptb_p": 0,
    "suara_tidak_sah": 34,
    "pengguna_total_j": 190,
    "pengguna_total_l": 88,
    "pengguna_total_p": 102,
    "pengguna_non_dpt_j": 1,
    "pengguna_non_dpt_l": 1,
    "pengguna_non_dpt_p": 0
  },
  "psu": null,
  "ts": "2024-02-16 16:25:41",
  "status_suara": true,
  "status_adm": true
}