{
  "mode": "hhcw",
  "chart": {
    "695854": 9,
    "695855": 18,
    "695856": 4,
    "695857": 14,
    "695858": 2,
    "695859": 5,
    "695860": 4,
    "695861": 7,
    "695862": 0,
    "695863": 20,
    "695864": 5,
    "695865": 1,
    "695866": 0,
    "695867": 7,
    "695868": 2,
    "695869": 3,
    "695870": 2,
    "695871": 4,
    "695872": 1,
    "695873": 1,
    "695874": 0,
    "695875": 20,
    "695876": 1,
    "695877": 0,
    "695878": 4,
    "695879": 1,
    "695880": 1,
    "695881": 1,
    "695882": 0,
    "695883": 0,
    "695884": 0,
    "695885": 0,
    "695886": 0,
    "695887": 0,
    "695888": 1,
    "695889": 0,
    "695890": 1,
    "695891": 8,
    "695892": 5,
    "695893": 1,
    "695894": 49,
    "695895": 0,
    "695896": 0,
    "695897": 0,
    "695898": 0,
    "695899": 2,
    "695900": 0,
    "695901": 1,
    "695902": 0,
    "695903": 2,
    "695904": 0,
    "695905": 1,
    "695906": 0,
    "695907": 0,
    "null": null
  },
  "images": [
    "https://sirekap-obj-formc.kpu.go.id/623f/pemilu/pdpd/32/06/04/20/10/3206042010007-20240215-003141--79015c49-c3d4-442f-8f0c-24019cc6684d.jpg",
    "https://sirekap-obj-formc.kpu.go.id/623f/pemilu/pdpd/32/06/04/20/10/3206042010007-20240215-003123--ea4d41d7-3db3-483f-abdd-a9b6ac3fe7e7.jpg",
    "https://sirekap-obj-formc.kpu.go.id/623f/pemilu/pdpd/32/06/04/20/10/3206042010007-20240217-183355--71057cb1-58bf-41a4-ba13-ce7780b79578.jpg",
    "https://sirekap-obj-formc.kpu.go.id/623f/pemilu/pdpd/32/06/04/20/10/3206042010007-20240217-183355--59f5131d-748f-4d17-9ba3-b02b5f7c14f9.jpg",
    "https://sirekap-obj-formc.kpu.go.id/623f/pemilu/pdpd/32/06/04/20/10/3206042010007-20240217-183356--f62351dc-239c-48b8-a13a-b6c60c999be3.jpg",
    "https://sirekap-obj-formc.kpu.go.id/623f/pemilu/pdpd/32/06/04/20/10/3206042010007-20240215-003915--0fad7ef1-1b34-471a-abf9-735208866d4b.jpg",
    "https://sirekap-obj-formc.kpu.go.id/623f/pemilu/pdpd/32/06/04/20/10/3206042010007-20240215-004038--7d46ca84-58cb-4523-a493-ef58850ea512.jpg"
  ],
  "administrasi": {
    "suara_sah": 214,
    "suara_total": 231,
    "pemilih_dpt_j": 276,
    "pemilih_dpt_l": 137,
    "pemilih_dpt_p": 139,
    "pengguna_dpt_j": 231,
    "pengguna_dpt_l": 108,
    "pengguna_dpt_p": 123,
    "pengguna_dptb_j": 0,
    "pengguna_dptb_l": 0,
    "pengguna_dptb_p": 0,
    "suara_tidak_sah": 17,
    "pengguna_total_j": 231,
    "pengguna_total_l": 108,
    "pengguna_total_p": 123,
    "pengguna_non_dpt_j": 0,
    "pengguna_non_dpt_l": 0,
    "pengguna_non_dpt_p": 0
  },
  "psu": null,
  "ts": "2024-02-17 19:00:04",
  "status_suara": true,
  "status_adm": true
}