{
  "chart": {
    "695637": 8,
    "695638": 6,
    "695639": 23,
    "695640": 0,
    "695641": 46,
    "695642": 2,
    "695643": 0,
    "695644": 0,
    "695645": 0,
    "695646": 0,
    "695647": 0,
    "695648": 0,
    "695649": 1,
    "695650": 0,
    "695651": 0,
    "695652": 0,
    "695653": 0,
    "695654": 0,
    "695655": 0,
    "695656": 0,
    "695657": 0,
    "695658": 7,
    "695659": 0,
    "695660": 0,
    "695661": 0,
    "695662": 0,
    "695663": 2,
    "695664": 0,
    "695665": 62,
    "695666": 0,
    "null": null
  },
  "images": [
    "https://sirekap-obj-formc.kpu.go.id/a6db/pemilu/pdpd/11/08/11/20/38/1108112038001-20240216-060429--5667b2e1-5005-40df-95b3-f45c79897a10.jpg",
    "https://sirekap-obj-formc.kpu.go.id/a6db/pemilu/pdpd/11/08/11/20/38/1108112038001-20240216-055012--4324107d-e16c-405b-b9f0-6d703d046145.jpg",
    "https://sirekap-obj-formc.kpu.go.id/a6db/pemilu/pdpd/11/08/11/20/38/1108112038001-20240216-055014--2d2d2fa9-7ed1-44a9-87de-72a446a1069d.jpg",
    "https://sirekap-obj-formc.kpu.go.id/a6db/pemilu/pdpd/11/08/11/20/38/1108112038001-20240216-055015--804fbe35-a277-40d8-b7a3-2fd45ccb8b52.jpg",
    "https://sirekap-obj-formc.kpu.go.id/a6db/pemilu/pdpd/11/08/11/20/38/1108112038001-20240216-055011--18b2ef40-b343-416c-ad42-0662ff60adfd.jpg"
  ],
  "administrasi": {
    "suara_sah": 157,
    "suara_total": 169,
    "pemilih_dpt_j": 173,
    "pemilih_dpt_l": 83,
    "pemilih_dpt_p": 90,
    "pengguna_dpt_j": 169,
    "pengguna_dpt_l": 81,
    "pengguna_dpt_p": 88,
    "pengguna_dptb_j": 0,
    "pengguna_dptb_l": 0,
    "pengguna_dptb_p": 0,
    "suara_tidak_sah": 12,
    "pengguna_total_j": 169,
    "pengguna_total_l": 81,
    "pengguna_total_p": 88,
    "pengguna_non_dpt_j": 0,
    "pengguna_non_dpt_l": 0,
    "pengguna_non_dpt_p": 0
  },
  "psu": null,
  "ts": "2024-02-16 06:31:15",
  "status_suara": true,
  "status_adm": true
}