{
  "mode": "hhcw",
  "chart": {
    "695854": 10,
    "695855": 15,
    "695856": 2,
    "695857": 12,
    "695858": 1,
    "695859": 8,
    "695860": 10,
    "695861": 800,
    "695862": 0,
    "695863": 825,
    "695864": 6,
    "695865": 0,
    "695866": 1,
    "695867": 14,
    "695868": 0,
    "695869": 1,
    "695870": 2,
    "695871": 2,
    "695872": 0,
    "695873": 1,
    "695874": 800,
    "695875": 5,
    "695876": 801,
    "695877": 80,
    "695878": 0,
    "695879": 1,
    "695880": 802,
    "695881": 0,
    "695882": 81,
    "695883": 8,
    "695884": 0,
    "695885": 1,
    "695886": 1,
    "695887": 1,
    "695888": 2,
    "695889": 0,
    "695890": 82,
    "695891": 882,
    "695892": 7,
    "695893": 0,
    "695894": 1,
    "695895": 4,
    "695896": 808,
    "695897": 0,
    "695898": 2,
    "695899": 88,
    "695900": 80,
    "695901": 80,
    "695902": 833,
    "695903": 888,
    "695904": 37,
    "695905": 88,
    "695906": 631,
    "695907": 553,
    "null": null
  },
  "images": [
    "https://sirekap-obj-formc.kpu.go.id/f0b8/pemilu/pdpd/32/02/21/20/09/3202212009007-20240217-194627--6dce8cb9-4e34-41a5-9b66-559c4f73cdc9.jpg",
    "https://sirekap-obj-formc.kpu.go.id/f0b8/pemilu/pdpd/32/02/21/20/09/3202212009007-20240217-194703--b2f72155-86e9-4e16-ac6a-9c1b7a0f7c26.jpg",
    "https://sirekap-obj-formc.kpu.go.id/f0b8/pemilu/pdpd/32/02/21/20/09/3202212009007-20240217-195158--a9f3dd29-9b1d-4167-8cb1-de44790c33f5.jpg",
    "https://sirekap-obj-formc.kpu.go.id/f0b8/pemilu/pdpd/32/02/21/20/09/3202212009007-20240217-195316--65a1f1d1-bb14-46c6-82ea-156155319b16.jpg",
    "https://sirekap-obj-formc.kpu.go.id/f0b8/pemilu/pdpd/32/02/21/20/09/3202212009007-20240217-195455--6ae205e3-5441-4e65-b0f7-1a7257e920bf.jpg",
    "https://sirekap-obj-formc.kpu.go.id/f0b8/pemilu/pdpd/32/02/21/20/09/3202212009007-20240217-195526--264df69b-b0c9-405d-a77f-2d71789da8af.jpg",
    "https://sirekap-obj-formc.kpu.go.id/f0b8/pemilu/pdpd/32/02/21/20/09/3202212009007-20240217-195611--18305267-4e8d-43af-bd3c-b8b0089c8256.jpg"
  ],
  "administrasi": {
    "suara_sah": 152,
    "suara_total": 184,
    "pemilih_dpt_j": 245,
    "pemilih_dpt_l": 127,
    "pemilih_dpt_p": 118,
    "pengguna_dpt_j": 0,
    "pengguna_dpt_l": 0,
    "pengguna_dpt_p": 0,
    "pengguna_dptb_j": 0,
    "pengguna_dptb_l": 0,
    "pengguna_dptb_p": 0,
    "suara_tidak_sah": 21,
    "pengguna_total_j": 184,
    "pengguna_total_l": 89,
    "pengguna_total_p": 95,
    "pengguna_non_dpt_j": 0,
    "pengguna_non_dpt_l": 0,
    "pengguna_non_dpt_p": 0
  },
  "psu": null,
  "ts": "2024-02-19 06:15:00",
  "status_suara": true,
  "status_adm": true
}