{
  "mode": "hhcw",
  "chart": {
    "695928": 21,
    "695929": 17,
    "695930": 21,
    "695931": 8,
    "695932": 20,
    "695933": 8,
    "695934": 10,
    "695935": 7,
    "695936": 2,
    "695937": 24,
    "695938": 2,
    "695939": 23,
    "695940": 3,
    "null": null
  },
  "images": [
    "https://sirekap-obj-formc.kpu.go.id/6241/pemilu/pdpd/35/06/14/20/12/3506142012001-20240217-175846--06710e51-e3b5-49ee-8cbf-54ccfabbe5d1.jpg",
    "https://sirekap-obj-formc.kpu.go.id/6241/pemilu/pdpd/35/06/14/20/12/3506142012001-20240217-175847--e6fb7e2a-352a-4269-b2a8-59fa1bcf3d33.jpg",
    "https://sirekap-obj-formc.kpu.go.id/6241/pemilu/pdpd/35/06/14/20/12/3506142012001-20240217-175848--9a1ac59d-f95e-4dea-a509-736ad9b4096a.jpg",
    "https://sirekap-obj-formc.kpu.go.id/6241/pemilu/pdpd/35/06/14/20/12/3506142012001-20240217-175847--dd2c2edd-b286-40fd-b7aa-d62cebbb9d1e.jpg"
  ],
  "administrasi": {
    "suara_sah": 166,
    "suara_total": 217,
    "pemilih_dpt_j": 258,
    "pemilih_dpt_l": 126,
    "pemilih_dpt_p": 132,
    "pengguna_dpt_j": 216,
    "pengguna_dpt_l": 102,
    "pengguna_dpt_p": 114,
    "pengguna_dptb_j": 1,
    "pengguna_dptb_l": 1,
    "pengguna_dptb_p": 0,
    "suara_tidak_sah": 51,
    "pengguna_total_j": 217,
    "pengguna_total_l": 103,
    "pengguna_total_p": 114,
    "pengguna_non_dpt_j": 0,
    "pengguna_non_dpt_l": 0,
    "pengguna_non_dpt_p": 0
  },
  "psu": null,
  "ts": "2024-02-17 18:00:00",
  "status_suara": true,
  "status_adm": true
}