{
  "chart": {
    "695908": 24,
    "695909": 6,
    "695910": 8,
    "695911": 22,
    "695912": 22,
    "695913": 18,
    "695914": 1,
    "695915": 5,
    "695916": 4,
    "695917": 35,
    "695918": 17,
    "null": null
  },
  "images": [
    "https://sirekap-obj-formc.kpu.go.id/0ca6/pemilu/pdpd/33/28/04/20/14/3328042014007-20240216-110336--0efaab2c-701f-41c1-8dd5-2ffdebf302f4.jpg",
    "https://sirekap-obj-formc.kpu.go.id/0ca6/pemilu/pdpd/33/28/04/20/14/3328042014007-20240216-112352--41017c8c-8c9d-4167-b70d-195e461b6963.jpg",
    "https://sirekap-obj-formc.kpu.go.id/0ca6/pemilu/pdpd/33/28/04/20/14/3328042014007-20240216-112350--89992146-f4cb-4094-97fa-a2801c17d6ed.jpg"
  ],
  "administrasi": {
    "suara_sah": 162,
    "suara_total": 226,
    "pemilih_dpt_j": 295,
    "pemilih_dpt_l": 143,
    "pemilih_dpt_p": 152,
    "pengguna_dpt_j": 225,
    "pengguna_dpt_l": 102,
    "pengguna_dpt_p": 123,
    "pengguna_dptb_j": 0,
    "pengguna_dptb_l": 0,
    "pengguna_dptb_p": 0,
    "suara_tidak_sah": 64,
    "pengguna_total_j": 226,
    "pengguna_total_l": 103,
    "pengguna_total_p": 123,
    "pengguna_non_dpt_j": 1,
    "pengguna_non_dpt_l": 1,
    "pengguna_non_dpt_p": 0
  },
  "psu": null,
  "ts": "2024-02-16 12:52:03",
  "status_suara": true,
  "status_adm": true
}