{
  "mode": "hhcw",
  "chart": {
    "696021": 14,
    "696022": 13,
    "696023": 1,
    "696024": 30,
    "696025": 1,
    "696026": 2,
    "696027": 28,
    "696028": 10,
    "696029": 2,
    "696030": 3,
    "696031": 3,
    "696032": 11,
    "696033": 11,
    "696034": 11,
    "696035": 0,
    "696036": 3,
    "null": null
  },
  "images": [
    "https://sirekap-obj-formc.kpu.go.id/7c02/pemilu/pdpd/61/04/05/20/07/6104052007002-20240217-095526--acd5bfe6-00bc-44a9-a185-8bd484d78b1e.jpg",
    "https://sirekap-obj-formc.kpu.go.id/7c02/pemilu/pdpd/61/04/05/20/07/6104052007002-20240217-095528--ba53385f-c43a-4622-8b66-12bd637fea35.jpg",
    "https://sirekap-obj-formc.kpu.go.id/7c02/pemilu/pdpd/61/04/05/20/07/6104052007002-20240217-095528--67fe8e61-6328-419a-bdfa-4c5ec7e8def0.jpg",
    "https://sirekap-obj-formc.kpu.go.id/7c02/pemilu/pdpd/61/04/05/20/07/6104052007002-20240217-095527--72573ef9-8e5f-4a98-9cc6-82a3ec32f647.jpg"
  ],
  "administrasi": {
    "suara_sah": 143,
    "suara_total": 187,
    "pemilih_dpt_j": 217,
    "pemilih_dpt_l": 112,
    "pemilih_dpt_p": 105,
    "pengguna_dpt_j": 181,
    "pengguna_dpt_l": 95,
    "pengguna_dpt_p": 86,
    "pengguna_dptb_j": 5,
    "pengguna_dptb_l": 3,
    "pengguna_dptb_p": 2,
    "suara_tidak_sah": 44,
    "pengguna_total_j": 187,
    "pengguna_total_l": 99,
    "pengguna_total_p": 88,
    "pengguna_non_dpt_j": 1,
    "pengguna_non_dpt_l": 1,
    "pengguna_non_dpt_p": 0
  },
  "psu": null,
  "ts": "2024-02-17 10:00:02",
  "status_suara": true,
  "status_adm": true
}