{
  "chart": {
    "695941": 12,
    "695942": 7,
    "695943": 8,
    "695944": 10,
    "695945": 9,
    "695946": 29,
    "695947": 2,
    "695948": 5,
    "695949": 5,
    "695950": 8,
    "695951": 5,
    "695952": 27,
    "695953": 1,
    "695954": 0,
    "695955": 0,
    "695956": 2,
    "695957": 1,
    "695958": 1,
    "695959": 2,
    "695960": 4,
    "695961": 1,
    "695962": 2,
    "695963": 4,
    "695964": 12
  },
  "images": [
    "https://sirekap-obj-formc.kpu.go.id/e81b/pemilu/pdpd/36/71/01/10/05/3671011005006-20240214-185705--cd2b2f6b-a194-4edf-bccd-91f7c96e3a0b.jpg",
    "https://sirekap-obj-formc.kpu.go.id/e81b/pemilu/pdpd/36/71/01/10/05/3671011005006-20240214-185708--65df6541-950c-411a-9cd2-3eaaaf6868bd.jpg",
    "https://sirekap-obj-formc.kpu.go.id/e81b/pemilu/pdpd/36/71/01/10/05/3671011005006-20240214-191111--f839df55-427d-4856-84f2-1319a06b2505.jpg",
    "https://sirekap-obj-formc.kpu.go.id/e81b/pemilu/pdpd/36/71/01/10/05/3671011005006-20240214-185715--63b4b644-6ea9-4cc9-9066-550016cdd2bd.jpg"
  ],
  "administrasi": {
    "suara_sah": 157,
    "suara_total": 177,
    "pemilih_dpt_j": 258,
    "pemilih_dpt_l": 136,
    "pemilih_dpt_p": 122,
    "pengguna_dpt_j": 176,
    "pengguna_dpt_l": 91,
    "pengguna_dpt_p": 85,
    "pengguna_dptb_j": 0,
    "pengguna_dptb_l": 0,
    "pengguna_dptb_p": 0,
    "suara_tidak_sah": 20,
    "pengguna_total_j": 177,
    "pengguna_total_l": 91,
    "pengguna_total_p": 86,
    "pengguna_non_dpt_j": 1,
    "pengguna_non_dpt_l": 0,
    "pengguna_non_dpt_p": 1
  },
  "psu": null,
  "ts": "2024-02-14 21:46:17",
  "status_suara": true,
  "status_adm": true
}