{
  "chart": {
    "695941": 8,
    "695942": 5,
    "695943": 5,
    "695944": 8,
    "695945": 7,
    "695946": 28,
    "695947": 3,
    "695948": 0,
    "695949": 3,
    "695950": 13,
    "695951": 0,
    "695952": 7,
    "695953": 2,
    "695954": 1,
    "695955": 42,
    "695956": 1,
    "695957": 0,
    "695958": 2,
    "695959": 27,
    "695960": 2,
    "695961": 1,
    "695962": 3,
    "695963": 6,
    "695964": 0
  },
  "images": [
    "https://sirekap-obj-formc.kpu.go.id/1f90/pemilu/pdpd/36/01/04/20/14/3601042014002-20240216-081622--6539e893-a27c-4b17-b405-8596be5ccd56.jpg",
    "https://sirekap-obj-formc.kpu.go.id/1f90/pemilu/pdpd/36/01/04/20/14/3601042014002-20240216-081634--5bb6c6f6-2bbd-416d-a914-0728578a032a.jpg",
    "https://sirekap-obj-formc.kpu.go.id/1f90/pemilu/pdpd/36/01/04/20/14/3601042014002-20240216-081643--2f397d2b-1d99-4c3a-8fb3-d5b18a20ba3e.jpg",
    "https://sirekap-obj-formc.kpu.go.id/1f90/pemilu/pdpd/36/01/04/20/14/3601042014002-20240216-081627--0f41320b-1e97-4cf3-a383-09782f719a10.jpg"
  ],
  "administrasi": {
    "suara_sah": 174,
    "suara_total": 213,
    "pemilih_dpt_j": 231,
    "pemilih_dpt_l": 106,
    "pemilih_dpt_p": 125,
    "pengguna_dpt_j": 211,
    "pengguna_dpt_l": 95,
    "pengguna_dpt_p": 116,
    "pengguna_dptb_j": 0,
    "pengguna_dptb_l": 0,
    "pengguna_dptb_p": 0,
    "suara_tidak_sah": 39,
    "pengguna_total_j": 213,
    "pengguna_total_l": 96,
    "pengguna_total_p": 117,
    "pengguna_non_dpt_j": 2,
    "pengguna_non_dpt_l": 1,
    "pengguna_non_dpt_p": 1
  },
  "psu": null,
  "ts": "2024-02-16 08:31:17",
  "status_suara": true,
  "status_adm": true
}