{
  "mode": "hhcw",
  "chart": {
    "695908": 15,
    "695909": 6,
    "695910": 1,
    "695911": 11,
    "695912": 28,
    "695913": 28,
    "695914": 3,
    "695915": 3,
    "695916": 5,
    "695917": 28,
    "695918": 25,
    "null": null
  },
  "images": [
    null,
    "https://sirekap-obj-formc.kpu.go.id/afce/pemilu/pdpd/33/06/06/10/14/3306061014010-20240214-204935--e1619853-fa4d-4a30-958a-3a9e0f35be2c.jpg",
    null
  ],
  "administrasi": null,
  "psu": null,
  "ts": "2024-02-19 06:15:00",
  "status_suara": true,
  "status_adm": false
}