{
  "chart": {
    "695908": 16,
    "695909": 17,
    "695910": 38,
    "695911": 15,
    "695912": 35,
    "695913": 7,
    "695914": 8,
    "695915": 5,
    "695916": 6,
    "695917": 12,
    "695918": 22,
    "null": null
  },
  "images": [
    "https://sirekap-obj-formc.kpu.go.id/f254/pemilu/pdpd/33/12/05/20/05/3312052005011-20240214-192254--ccb86a26-5ebc-422d-ab4e-eedf9fc00c08.jpg",
    "https://sirekap-obj-formc.kpu.go.id/f254/pemilu/pdpd/33/12/05/20/05/3312052005011-20240214-192252--18914b8a-245f-4473-a82c-b3508917beb6.jpg",
    "https://sirekap-obj-formc.kpu.go.id/f254/pemilu/pdpd/33/12/05/20/05/3312052005011-20240214-192257--e0a4c791-6066-49e1-820d-95077e719b39.jpg"
  ],
  "administrasi": {
    "suara_sah": 181,
    "suara_total": 184,
    "pemilih_dpt_j": 279,
    "pemilih_dpt_l": 145,
    "pemilih_dpt_p": 134,
    "pengguna_dpt_j": 183,
    "pengguna_dpt_l": 81,
    "pengguna_dpt_p": 102,
    "pengguna_dptb_j": 0,
    "pengguna_dptb_l": 0,
    "pengguna_dptb_p": 0,
    "suara_tidak_sah": 3,
    "pengguna_total_j": 184,
    "pengguna_total_l": 82,
    "pengguna_total_p": 102,
    "pengguna_non_dpt_j": 1,
    "pengguna_non_dpt_l": 1,
    "pengguna_non_dpt_p": 0
  },
  "psu": null,
  "ts": "2024-02-14 21:46:17",
  "status_suara": true,
  "status_adm": true
}