{
  "mode": "hhcw",
  "chart": {
    "695908": 16,
    "695909": 8,
    "695910": 5,
    "695911": 7,
    "695912": 52,
    "695913": 26,
    "695914": 6,
    "695915": 4,
    "695916": 5,
    "695917": 22,
    "695918": 41,
    "null": null
  },
  "images": [
    "https://sirekap-obj-formc.kpu.go.id/466d/pemilu/pdpd/33/16/05/10/14/3316051014012-20240218-170629--4902848c-5b3c-4c2f-a860-d4a69f686709.jpg",
    "https://sirekap-obj-formc.kpu.go.id/466d/pemilu/pdpd/33/16/05/10/14/3316051014012-20240218-170631--bb00dd69-7fad-42a5-b074-3803ee815274.jpg",
    "https://sirekap-obj-formc.kpu.go.id/466d/pemilu/pdpd/33/16/05/10/14/3316051014012-20240218-170630--2f76a882-fda1-499a-8607-e74c5f2a5ded.jpg"
  ],
  "administrasi": {
    "suara_sah": 192,
    "suara_total": 225,
    "pemilih_dpt_j": 292,
    "pemilih_dpt_l": 145,
    "pemilih_dpt_p": 147,
    "pengguna_dpt_j": 216,
    "pengguna_dpt_l": 107,
    "pengguna_dpt_p": 109,
    "pengguna_dptb_j": 3,
    "pengguna_dptb_l": 2,
    "pengguna_dptb_p": 1,
    "suara_tidak_sah": 33,
    "pengguna_total_j": 225,
    "pengguna_total_l": 111,
    "pengguna_total_p": 114,
    "pengguna_non_dpt_j": 6,
    "pengguna_non_dpt_l": 2,
    "pengguna_non_dpt_p": 4
  },
  "psu": null,
  "ts": "2024-02-19 06:15:00",
  "status_suara": true,
  "status_adm": true
}