{
  "mode": "hhcw",
  "chart": {
    "696046": 7,
    "696047": 5,
    "696048": 60,
    "696049": 12,
    "696050": 27,
    "696051": 17,
    "696052": 22,
    "696053": 0,
    "696054": 3,
    "null": null
  },
  "images": [
    "https://sirekap-obj-formc.kpu.go.id/ed8a/pemilu/pdpd/63/11/06/20/24/6311062024001-20240216-163810--0bdffe6b-0bee-47b8-8ee5-66bd8692b4fc.jpg",
    "https://sirekap-obj-formc.kpu.go.id/ed8a/pemilu/pdpd/63/11/06/20/24/6311062024001-20240216-163811--18c42be2-3109-4948-8f75-37d4fbd48191.jpg",
    "https://sirekap-obj-formc.kpu.go.id/ed8a/pemilu/pdpd/63/11/06/20/24/6311062024001-20240216-163810--82dbf949-efed-416f-802f-9f1a28aa03cf.jpg"
  ],
  "administrasi": {
    "suara_sah": 153,
    "suara_total": 189,
    "pemilih_dpt_j": 203,
    "pemilih_dpt_l": 101,
    "pemilih_dpt_p": 102,
    "pengguna_dpt_j": 187,
    "pengguna_dpt_l": 93,
    "pengguna_dpt_p": 94,
    "pengguna_dptb_j": 1,
    "pengguna_dptb_l": 1,
    "pengguna_dptb_p": 0,
    "suara_tidak_sah": 36,
    "pengguna_total_j": 189,
    "pengguna_total_l": 94,
    "pengguna_total_p": 95,
    "pengguna_non_dpt_j": 1,
    "pengguna_non_dpt_l": 0,
    "pengguna_non_dpt_p": 1
  },
  "psu": null,
  "ts": "2024-02-16 16:57:39",
  "status_suara": true,
  "status_adm": true
}