{
  "mode": "hhcw",
  "chart": {
    "695941": 13,
    "695942": 2,
    "695943": 3,
    "695944": 17,
    "695945": 4,
    "695946": 15,
    "695947": 4,
    "695948": 1,
    "695949": 10,
    "695950": 10,
    "695951": 1,
    "695952": 22,
    "695953": 1,
    "695954": 0,
    "695955": 0,
    "695956": 0,
    "695957": 1,
    "695958": 1,
    "695959": 4,
    "695960": 2,
    "695961": 4,
    "695962": 1,
    "695963": 9,
    "695964": 0
  },
  "images": [
    null,
    "https://sirekap-obj-formc.kpu.go.id/c73a/pemilu/pdpd/36/03/32/20/08/3603322008001-20240217-141255--bd415091-91e5-40bc-ad29-b7fec1adde66.jpg",
    "https://sirekap-obj-formc.kpu.go.id/c73a/pemilu/pdpd/36/03/32/20/08/3603322008001-20240217-142059--474d0bae-8405-4193-9fa9-7d34444cc96a.jpg",
    null
  ],
  "administrasi": null,
  "psu": null,
  "ts": "2024-02-20 17:00:00",
  "status_suara": true,
  "status_adm": false
}