{
  "mode": "hhcw",
  "chart": {
    "695965": 30,
    "695966": 3,
    "695967": 1,
    "695968": 2,
    "695969": 16,
    "695970": 0,
    "695971": 1,
    "695972": 1,
    "695973": 21,
    "695974": 0,
    "695975": 88,
    "695976": 8,
    "695977": 0,
    "695978": 0,
    "695979": 16,
    "695980": 0,
    "695981": 30,
    "null": null
  },
  "images": [
    "https://sirekap-obj-formc.kpu.go.id/11ee/pemilu/pdpd/51/07/07/20/03/5107072003014-20240216-005947--9a3056b3-4731-44e1-a71b-fcc43505cba7.jpg",
    "https://sirekap-obj-formc.kpu.go.id/11ee/pemilu/pdpd/51/07/07/20/03/5107072003014-20240216-005952--6d44de23-16d4-4117-a25c-a5d8d47682ee.jpg",
    "https://sirekap-obj-formc.kpu.go.id/11ee/pemilu/pdpd/51/07/07/20/03/5107072003014-20240216-005954--a8d479ec-a9ab-44f5-a32b-c33901db1029.jpg",
    "https://sirekap-obj-formc.kpu.go.id/11ee/pemilu/pdpd/51/07/07/20/03/5107072003014-20240216-005949--c0a516cd-bbdb-4bff-94e2-e44d1f5278a0.jpg"
  ],
  "administrasi": {
    "suara_sah": 217,
    "suara_total": 241,
    "pemilih_dpt_j": 261,
    "pemilih_dpt_l": 120,
    "pemilih_dpt_p": 141,
    "pengguna_dpt_j": 241,
    "pengguna_dpt_l": 109,
    "pengguna_dpt_p": 132,
    "pengguna_dptb_j": 0,
    "pengguna_dptb_l": 0,
    "pengguna_dptb_p": 0,
    "suara_tidak_sah": 24,
    "pengguna_total_j": 241,
    "pengguna_total_l": 109,
    "pengguna_total_p": 132,
    "pengguna_non_dpt_j": 0,
    "pengguna_non_dpt_l": 0,
    "pengguna_non_dpt_p": 0
  },
  "psu": null,
  "ts": "2024-02-17 14:45:17",
  "status_suara": true,
  "status_adm": true
}