{
  "chart": {
    "695908": 32,
    "695909": 5,
    "695910": 10,
    "695911": 23,
    "695912": 38,
    "695913": 23,
    "695914": 6,
    "695915": 2,
    "695916": 12,
    "695917": 27,
    "695918": 21,
    "null": null
  },
  "images": [
    "https://sirekap-obj-formc.kpu.go.id/216f/pemilu/pdpd/33/01/13/20/01/3301132001008-20240216-124420--ded30ec7-6a64-452f-92cd-7b70bfb91f06.jpg",
    "https://sirekap-obj-formc.kpu.go.id/216f/pemilu/pdpd/33/01/13/20/01/3301132001008-20240216-124430--62297d27-8fc5-4789-ae80-1f2f94ddabad.jpg",
    "https://sirekap-obj-formc.kpu.go.id/216f/pemilu/pdpd/33/01/13/20/01/3301132001008-20240216-124424--58559570-c0aa-403d-be8e-c682727d5070.jpg"
  ],
  "administrasi": {
    "suara_sah": 199,
    "suara_total": 215,
    "pemilih_dpt_j": 274,
    "pemilih_dpt_l": 136,
    "pemilih_dpt_p": 138,
    "pengguna_dpt_j": 211,
    "pengguna_dpt_l": 96,
    "pengguna_dpt_p": 115,
    "pengguna_dptb_j": 2,
    "pengguna_dptb_l": 1,
    "pengguna_dptb_p": 1,
    "suara_tidak_sah": 16,
    "pengguna_total_j": 215,
    "pengguna_total_l": 98,
    "pengguna_total_p": 117,
    "pengguna_non_dpt_j": 2,
    "pengguna_non_dpt_l": 1,
    "pengguna_non_dpt_p": 1
  },
  "psu": null,
  "ts": "2024-02-16 12:52:03",
  "status_suara": true,
  "status_adm": true
}