{
  "mode": "hhcw",
  "chart": {
    "695928": 18,
    "695929": 31,
    "695930": 18,
    "695931": 14,
    "695932": 21,
    "695933": 16,
    "695934": 4,
    "695935": 2,
    "695936": 2,
    "695937": 20,
    "695938": 1,
    "695939": 34,
    "695940": 1,
    "null": null
  },
  "images": [
    "https://sirekap-obj-formc.kpu.go.id/a1e6/pemilu/pdpd/35/16/10/20/08/3516102008005-20240218-182844--4c215cce-a902-4761-9fbc-dfb77f46b20c.jpg",
    "https://sirekap-obj-formc.kpu.go.id/a1e6/pemilu/pdpd/35/16/10/20/08/3516102008005-20240218-182845--4a2bad58-0372-4a66-b940-c5875779f103.jpg",
    "https://sirekap-obj-formc.kpu.go.id/a1e6/pemilu/pdpd/35/16/10/20/08/3516102008005-20240218-182846--92dcb9e2-5782-491d-be9a-51219ed2d0d8.jpg",
    "https://sirekap-obj-formc.kpu.go.id/a1e6/pemilu/pdpd/35/16/10/20/08/3516102008005-20240218-182844--a5e05886-8020-42d6-913f-933caeba0235.jpg"
  ],
  "administrasi": {
    "suara_sah": 182,
    "suara_total": 257,
    "pemilih_dpt_j": 288,
    "pemilih_dpt_l": 142,
    "pemilih_dpt_p": 146,
    "pengguna_dpt_j": 257,
    "pengguna_dpt_l": 125,
    "pengguna_dpt_p": 132,
    "pengguna_dptb_j": 0,
    "pengguna_dptb_l": 0,
    "pengguna_dptb_p": 0,
    "suara_tidak_sah": 75,
    "pengguna_total_j": 257,
    "pengguna_total_l": 125,
    "pengguna_total_p": 132,
    "pengguna_non_dpt_j": 0,
    "pengguna_non_dpt_l": 0,
    "pengguna_non_dpt_p": 0
  },
  "psu": null,
  "ts": "2024-02-19 06:15:00",
  "status_suara": true,
  "status_adm": true
}