{
  "chart": {
    "695919": 20,
    "695920": 74,
    "695921": 1,
    "695922": 31,
    "695923": 6,
    "695924": 5,
    "695925": 1,
    "695926": 2,
    "695927": 3,
    "null": null
  },
  "images": [
    "https://sirekap-obj-formc.kpu.go.id/4dbb/pemilu/pdpd/34/03/11/20/08/3403112008013-20240216-055157--c4188a17-c354-4a79-a719-10d1c3ac555c.jpg",
    "https://sirekap-obj-formc.kpu.go.id/4dbb/pemilu/pdpd/34/03/11/20/08/3403112008013-20240216-055200--ac3170a7-8bff-46fc-99a4-f032e818bead.jpg",
    "https://sirekap-obj-formc.kpu.go.id/4dbb/pemilu/pdpd/34/03/11/20/08/3403112008013-20240216-055159--3cc96a31-17a8-45ac-8eac-46ea6676aea4.jpg"
  ],
  "administrasi": {
    "suara_sah": 143,
    "suara_total": 149,
    "pemilih_dpt_j": 172,
    "pemilih_dpt_l": 82,
    "pemilih_dpt_p": 90,
    "pengguna_dpt_j": 147,
    "pengguna_dpt_l": 67,
    "pengguna_dpt_p": 80,
    "pengguna_dptb_j": 2,
    "pengguna_dptb_l": 1,
    "pengguna_dptb_p": 1,
    "suara_tidak_sah": 6,
    "pengguna_total_j": 149,
    "pengguna_total_l": 68,
    "pengguna_total_p": 81,
    "pengguna_non_dpt_j": 0,
    "pengguna_non_dpt_l": 0,
    "pengguna_non_dpt_p": 0
  },
  "psu": null,
  "ts": "2024-02-16 06:01:13",
  "status_suara": true,
  "status_adm": true
}