{
  "mode": "hhcw",
  "chart": {
    "695688": 57,
    "695689": 10,
    "695690": 6,
    "695691": 2,
    "695692": 8,
    "695693": 4,
    "695694": 0,
    "695695": 3,
    "695696": 9,
    "695697": 2,
    "695698": 6,
    "695699": 3,
    "695700": 0,
    "695701": 3,
    "695702": 2,
    "null": null
  },
  "images": [
    "https://sirekap-obj-formc.kpu.go.id/3b82/pemilu/pdpd/13/04/12/20/01/1304122001031-20240216-144446--f92483aa-2cf9-43d9-9341-f484664ab33f.jpg",
    "https://sirekap-obj-formc.kpu.go.id/3b82/pemilu/pdpd/13/04/12/20/01/1304122001031-20240216-144447--13d7775e-9962-4aa5-8a5b-1492890963c8.jpg",
    "https://sirekap-obj-formc.kpu.go.id/3b82/pemilu/pdpd/13/04/12/20/01/1304122001031-20240216-144448--328efff0-970a-481d-b3e8-c7015a7f7c23.jpg",
    "https://sirekap-obj-formc.kpu.go.id/3b82/pemilu/pdpd/13/04/12/20/01/1304122001031-20240216-144446--3ca4e1fa-eab0-4d52-8896-c51b3f8ae94d.jpg"
  ],
  "administrasi": {
    "suara_sah": 123,
    "suara_total": 139,
    "pemilih_dpt_j": 197,
    "pemilih_dpt_l": 101,
    "pemilih_dpt_p": 96,
    "pengguna_dpt_j": 138,
    "pengguna_dpt_l": 68,
    "pengguna_dpt_p": 70,
    "pengguna_dptb_j": 1,
    "pengguna_dptb_l": 0,
    "pengguna_dptb_p": 1,
    "suara_tidak_sah": 16,
    "pengguna_total_j": 139,
    "pengguna_total_l": 68,
    "pengguna_total_p": 71,
    "pengguna_non_dpt_j": 0,
    "pengguna_non_dpt_l": 0,
    "pengguna_non_dpt_p": 0
  },
  "psu": null,
  "ts": "2024-02-16 16:25:41",
  "status_suara": true,
  "status_adm": true
}