{
  "chart": {
    "695928": 25,
    "695929": 26,
    "695930": 18,
    "695931": 26,
    "695932": 33,
    "695933": 26,
    "695934": 4,
    "695935": 6,
    "695936": 1,
    "695937": 30,
    "695938": 1,
    "695939": 26,
    "695940": 1,
    "null": null
  },
  "images": [
    "https://sirekap-obj-formc.kpu.go.id/8f56/pemilu/pdpd/35/08/07/20/01/3508072001010-20240216-080434--bc85650c-1a81-4ccd-bbef-26a928018646.jpg",
    "https://sirekap-obj-formc.kpu.go.id/8f56/pemilu/pdpd/35/08/07/20/01/3508072001010-20240216-080447--d2b559ac-1e6d-49a1-86a0-1e5b35fb03f4.jpg",
    "https://sirekap-obj-formc.kpu.go.id/8f56/pemilu/pdpd/35/08/07/20/01/3508072001010-20240216-080455--22f6af24-c64c-4dd9-83b2-89c0121ef9b5.jpg",
    "https://sirekap-obj-formc.kpu.go.id/8f56/pemilu/pdpd/35/08/07/20/01/3508072001010-20240216-080443--9389bfb4-f31a-4029-a27a-b74352ea6a30.jpg"
  ],
  "administrasi": {
    "suara_sah": 223,
    "suara_total": 255,
    "pemilih_dpt_j": 277,
    "pemilih_dpt_l": 139,
    "pemilih_dpt_p": 138,
    "pengguna_dpt_j": 251,
    "pengguna_dpt_l": 124,
    "pengguna_dpt_p": 127,
    "pengguna_dptb_j": 2,
    "pengguna_dptb_l": 1,
    "pengguna_dptb_p": 1,
    "suara_tidak_sah": 32,
    "pengguna_total_j": 255,
    "pengguna_total_l": 126,
    "pengguna_total_p": 129,
    "pengguna_non_dpt_j": 2,
    "pengguna_non_dpt_l": 1,
    "pengguna_non_dpt_p": 1
  },
  "psu": null,
  "ts": "2024-02-16 08:31:17",
  "status_suara": true,
  "status_adm": true
}