{
  "chart": {
    "695771": 2,
    "695772": 6,
    "695773": 0,
    "695774": 7,
    "695775": 47,
    "695776": 2,
    "695777": 75,
    "695778": 2,
    "695779": 3,
    "695780": 1,
    "695781": 0,
    "695782": 1
  },
  "images": [
    "https://sirekap-obj-formc.kpu.go.id/3b29/pemilu/pdpd/17/09/02/20/14/1709022014002-20240214-191230--4433e89c-8792-479a-b612-5ecdc8c45f37.jpg",
    "https://sirekap-obj-formc.kpu.go.id/3b29/pemilu/pdpd/17/09/02/20/14/1709022014002-20240214-191252--5ac69e50-6e63-41a9-b958-bbd6853fbd03.jpg",
    "https://sirekap-obj-formc.kpu.go.id/3b29/pemilu/pdpd/17/09/02/20/14/1709022014002-20240214-191241--09a65300-121c-4b63-9370-f7ef0e6b017e.jpg"
  ],
  "administrasi": {
    "suara_sah": 146,
    "suara_total": 159,
    "pemilih_dpt_j": 185,
    "pemilih_dpt_l": 98,
    "pemilih_dpt_p": 87,
    "pengguna_dpt_j": 158,
    "pengguna_dpt_l": 78,
    "pengguna_dpt_p": 80,
    "pengguna_dptb_j": 0,
    "pengguna_dptb_l": 0,
    "pengguna_dptb_p": 0,
    "suara_tidak_sah": 13,
    "pengguna_total_j": 159,
    "pengguna_total_l": 79,
    "pengguna_total_p": 80,
    "pengguna_non_dpt_j": 1,
    "pengguna_non_dpt_l": 1,
    "pengguna_non_dpt_p": 0
  },
  "psu": null,
  "ts": "2024-02-14 21:46:17",
  "status_suara": true,
  "status_adm": true
}