{
  "mode": "hhcw",
  "chart": {
    "695928": 11,
    "695929": 32,
    "695930": 12,
    "695931": 16,
    "695932": 17,
    "695933": 7,
    "695934": 1,
    "695935": 8,
    "695936": 0,
    "695937": 18,
    "695938": 1,
    "695939": 19,
    "695940": 2,
    "null": null
  },
  "images": [
    null,
    "https://sirekap-obj-formc.kpu.go.id/0e70/pemilu/pdpd/35/75/03/10/05/3575031005010-20240217-195934--572a0377-304a-4c4a-8b2f-56a214061386.jpg",
    "https://sirekap-obj-formc.kpu.go.id/0e70/pemilu/pdpd/35/75/03/10/05/3575031005010-20240217-195945--db57b3b3-4b60-42d2-bbb8-43ae5cf12c0d.jpg",
    null
  ],
  "administrasi": null,
  "psu": null,
  "ts": "2024-02-19 11:00:00",
  "status_suara": true,
  "status_adm": false
}