{
  "mode": "hhcw",
  "chart": {
    "695854": 37,
    "695855": 14,
    "695856": 2,
    "695857": 4,
    "695858": 1,
    "695859": 6,
    "695860": 4,
    "695861": 4,
    "695862": 0,
    "695863": 21,
    "695864": 7,
    "695865": 0,
    "695866": 1,
    "695867": 8,
    "695868": 1,
    "695869": 3,
    "695870": 3,
    "695871": 0,
    "695872": 1,
    "695873": 0,
    "695874": 0,
    "695875": 1,
    "695876": 0,
    "695877": 1,
    "695878": 0,
    "695879": 2,
    "695880": 0,
    "695881": 0,
    "695882": 1,
    "695883": 0,
    "695884": 0,
    "695885": 2,
    "695886": 1,
    "695887": 1,
    "695888": 1,
    "695889": 0,
    "695890": 1,
    "695891": 1,
    "695892": 1,
    "695893": 2,
    "695894": 1,
    "695895": 1,
    "695896": 0,
    "695897": 0,
    "695898": 1,
    "695899": 0,
    "695900": 0,
    "695901": 0,
    "695902": 0,
    "695903": 1,
    "695904": 0,
    "695905": 0,
    "695906": 0,
    "695907": 0,
    "null": null
  },
  "images": [
    "https://sirekap-obj-formc.kpu.go.id/5a9a/pemilu/pdpd/32/02/14/20/03/3202142003008-20240216-164601--95a9da88-2d3c-49f3-855f-90be942994c3.jpg",
    "https://sirekap-obj-formc.kpu.go.id/5a9a/pemilu/pdpd/32/02/14/20/03/3202142003008-20240216-164820--c224bfe1-3728-47cc-95db-65a9ee2ad9fa.jpg",
    "https://sirekap-obj-formc.kpu.go.id/5a9a/pemilu/pdpd/32/02/14/20/03/3202142003008-20240216-164912--111d9cec-215e-4946-8858-c1321efbe7ef.jpg",
    "https://sirekap-obj-formc.kpu.go.id/5a9a/pemilu/pdpd/32/02/14/20/03/3202142003008-20240216-165006--8244715f-a559-48aa-acba-c5dcab9821b5.jpg",
    "https://sirekap-obj-formc.kpu.go.id/5a9a/pemilu/pdpd/32/02/14/20/03/3202142003008-20240216-170623--e628c342-957e-4dec-8bc5-7c2b929c4c00.jpg",
    "https://sirekap-obj-formc.kpu.go.id/5a9a/pemilu/pdpd/32/02/14/20/03/3202142003008-20240216-165335--452e6f6a-859d-4779-a6aa-37169d484079.jpg",
    "https://sirekap-obj-formc.kpu.go.id/5a9a/pemilu/pdpd/32/02/14/20/03/3202142003008-20240216-165422--7c8dd836-c9ef-49e9-a86b-d0dedb1bcae6.jpg"
  ],
  "administrasi": {
    "suara_sah": 146,
    "suara_total": 225,
    "pemilih_dpt_j": 286,
    "pemilih_dpt_l": 151,
    "pemilih_dpt_p": 135,
    "pengguna_dpt_j": 223,
    "pengguna_dpt_l": 112,
    "pengguna_dpt_p": 111,
    "pengguna_dptb_j": 0,
    "pengguna_dptb_l": 0,
    "pengguna_dptb_p": 0,
    "suara_tidak_sah": 79,
    "pengguna_total_j": 225,
    "pengguna_total_l": 114,
    "pengguna_total_p": 111,
    "pengguna_non_dpt_j": 2,
    "pengguna_non_dpt_l": 2,
    "pengguna_non_dpt_p": 0
  },
  "psu": null,
  "ts": "2024-02-16 17:30:00",
  "status_suara": true,
  "status_adm": true
}