{
  "chart": {
    "695908": 26,
    "695909": 8,
    "695910": 6,
    "695911": 19,
    "695912": 43,
    "695913": 21,
    "695914": 13,
    "695915": 4,
    "695916": 7,
    "695917": 25,
    "695918": 38,
    "null": null
  },
  "images": [
    "https://sirekap-obj-formc.kpu.go.id/c683/pemilu/pdpd/33/74/15/10/05/3374151005004-20240214-204109--a103cb69-4bb0-4421-a45b-c78123fdd9b9.jpg",
    "https://sirekap-obj-formc.kpu.go.id/c683/pemilu/pdpd/33/74/15/10/05/3374151005004-20240214-204228--925202f8-06e2-4350-bf83-103aadd98f35.jpg",
    "https://sirekap-obj-formc.kpu.go.id/c683/pemilu/pdpd/33/74/15/10/05/3374151005004-20240214-204351--2e63e854-b1c4-4e4f-b96b-b2e26582e6e3.jpg"
  ],
  "administrasi": {
    "suara_sah": 210,
    "suara_total": 272,
    "pemilih_dpt_j": 295,
    "pemilih_dpt_l": 146,
    "pemilih_dpt_p": 149,
    "pengguna_dpt_j": 267,
    "pengguna_dpt_l": 130,
    "pengguna_dpt_p": 137,
    "pengguna_dptb_j": 3,
    "pengguna_dptb_l": 1,
    "pengguna_dptb_p": 2,
    "suara_tidak_sah": 62,
    "pengguna_total_j": 272,
    "pengguna_total_l": 132,
    "pengguna_total_p": 140,
    "pengguna_non_dpt_j": 2,
    "pengguna_non_dpt_l": 1,
    "pengguna_non_dpt_p": 1
  },
  "psu": null,
  "ts": "2024-02-15 00:40:47",
  "status_suara": true,
  "status_adm": true
}