{
  "chart": {
    "695908": 15,
    "695909": 4,
    "695910": 8,
    "695911": 11,
    "695912": 9,
    "695913": 11,
    "695914": 3,
    "695915": 1,
    "695916": 4,
    "695917": 11,
    "695918": 42,
    "null": null
  },
  "images": [
    "https://sirekap-obj-formc.kpu.go.id/a69e/pemilu/pdpd/33/27/03/20/10/3327032010012-20240216-133008--cdb79e86-fb00-41c8-9362-5fb407eb58e5.jpg",
    "https://sirekap-obj-formc.kpu.go.id/a69e/pemilu/pdpd/33/27/03/20/10/3327032010012-20240216-133009--f4167d72-e50a-48b3-b65a-c5849b5339e6.jpg",
    "https://sirekap-obj-formc.kpu.go.id/a69e/pemilu/pdpd/33/27/03/20/10/3327032010012-20240216-133009--649c99fa-d130-44a7-80ae-e2ca94246447.jpg"
  ],
  "administrasi": {
    "suara_sah": 119,
    "suara_total": 138,
    "pemilih_dpt_j": 191,
    "pemilih_dpt_l": 94,
    "pemilih_dpt_p": 97,
    "pengguna_dpt_j": 138,
    "pengguna_dpt_l": 53,
    "pengguna_dpt_p": 85,
    "pengguna_dptb_j": 0,
    "pengguna_dptb_l": 0,
    "pengguna_dptb_p": 0,
    "suara_tidak_sah": 19,
    "pengguna_total_j": 138,
    "pengguna_total_l": 53,
    "pengguna_total_p": 85,
    "pengguna_non_dpt_j": 0,
    "pengguna_non_dpt_l": 0,
    "pengguna_non_dpt_p": 0
  },
  "psu": null,
  "ts": "2024-02-16 14:01:43",
  "status_suara": true,
  "status_adm": true
}