{
  "mode": "hhcw",
  "chart": {
    "695928": 18,
    "695929": 33,
    "695930": 19,
    "695931": 15,
    "695932": 23,
    "695933": 16,
    "695934": 1,
    "695935": 3,
    "695936": 1,
    "695937": 22,
    "695938": 1,
    "695939": 26,
    "695940": 2,
    "null": null
  },
  "images": [
    "https://sirekap-obj-formc.kpu.go.id/3de1/pemilu/pdpd/35/25/16/10/06/3525161006010-20240216-152426--c01eae67-2f98-4149-be4a-67fd4f7d176a.jpg",
    "https://sirekap-obj-formc.kpu.go.id/3de1/pemilu/pdpd/35/25/16/10/06/3525161006010-20240216-152428--8d87acc8-61a9-48ea-b81e-370030bd9ecc.jpg",
    "https://sirekap-obj-formc.kpu.go.id/3de1/pemilu/pdpd/35/25/16/10/06/3525161006010-20240216-152428--9adf1dcb-f555-486b-961f-bb12bc54d028.jpg",
    "https://sirekap-obj-formc.kpu.go.id/3de1/pemilu/pdpd/35/25/16/10/06/3525161006010-20240216-152427--ab0c8938-a834-4fa0-8ffc-9bb5f680f6f3.jpg"
  ],
  "administrasi": {
    "suara_sah": 180,
    "suara_total": 228,
    "pemilih_dpt_j": 256,
    "pemilih_dpt_l": 129,
    "pemilih_dpt_p": 127,
    "pengguna_dpt_j": 228,
    "pengguna_dpt_l": 113,
    "pengguna_dpt_p": 115,
    "pengguna_dptb_j": 0,
    "pengguna_dptb_l": 0,
    "pengguna_dptb_p": 0,
    "suara_tidak_sah": 48,
    "pengguna_total_j": 228,
    "pengguna_total_l": 113,
    "pengguna_total_p": 115,
    "pengguna_non_dpt_j": 0,
    "pengguna_non_dpt_l": 0,
    "pengguna_non_dpt_p": 0
  },
  "psu": null,
  "ts": "2024-02-16 16:25:41",
  "status_suara": true,
  "status_adm": true
}